README.md
setup.cfg
setup.py
Algmarket/__init__.py
Algmarket/acl.py
Algmarket/algm_response.py
Algmarket/algorithm.py
Algmarket/async_response.py
Algmarket/client.py
Algmarket/data.py
Algmarket/datadirectory.py
Algmarket/datafile.py
Algmarket/errors.py
Algmarket/model.py
Algmarket/modeldirectory.py
Algmarket/modelfile.py
Algmarket/util.py
algmarket.egg-info/PKG-INFO
algmarket.egg-info/SOURCES.txt
algmarket.egg-info/dependency_links.txt
algmarket.egg-info/requires.txt
algmarket.egg-info/top_level.txt